{"entries":[{"id":"ireneo-isa-55-8","title":"Libro II, Capítulo 13 — Dios no es como los hombres en Sus pensamientos","author":"Ireneo de Lyon","reference":{"book":"ISA","chapterStart":55,"verseStart":8,"chapterEnd":55,"verseEnd":8},"content":"<p>Si hubieran conocido las Escrituras y hubieran sido enseñados por la verdad, habrían sabido, sin lugar a dudas, que Dios no es como los hombres, y que Sus pensamientos no son como los pensamientos de los hombres. Porque el Padre de todos está a una gran distancia de esos afectos y pasiones que operan entre los hombres. Él es un Ser simple, sin complejidad, sin miembros diversos, y totalmente semejante e igual a sí mismo.</p>"}]}